example_pkg/__init__.py
tests/__init__.py
tests/test_example_pkg.py
example_pkg_zumrudu_anka-0.0.3.dist-info/LICENSE
example_pkg_zumrudu_anka-0.0.3.dist-info/METADATA
example_pkg_zumrudu_anka-0.0.3.dist-info/WHEEL
example_pkg_zumrudu_anka-0.0.3.dist-info/top_level.txt
example_pkg_zumrudu_anka-0.0.3.dist-info/RECORD
