Metadata-Version: 2.1
Name: example-pkg-zumrudu-anka
Version: 0.0.3
Summary: A small example package
Home-page: https://github.com/zumrudu-anka/python-upload-package-boilerplate
Author: Zümrüd-ü Anka
Author-email: osmandurdag@hotmail.com
License: UNKNOWN
Keywords: upload-python-package calculator
Platform: UNKNOWN
Classifier: Programming Language :: Python :: 3.7
Classifier: License :: OSI Approved :: MIT License
Classifier: Operating System :: OS Independent
Classifier: Intended Audience :: Education
Classifier: Development Status :: 5 - Production/Stable
Classifier: Topic :: Software Development
Requires-Python: >=3
